weartsdk/MiddlewareStatusListener.py
weartsdk/WeArtAnalogSensorData.py
weartsdk/WeArtClient.py
weartsdk/WeArtCommon.py
weartsdk/WeArtEffect.py
weartsdk/WeArtForce.py
weartsdk/WeArtHapticObject.py
weartsdk/WeArtMessageListener.py
weartsdk/WeArtMessageSerializer.py
weartsdk/WeArtMessages.py
weartsdk/WeArtTemperature.py
weartsdk/WeArtTexture.py
weartsdk/WeArtThimbleTrackingObject.py
weartsdk/WeArtTrackingCalibration.py
weartsdk/WeArtTrackingRawData.py
weartsdk/__init__.py
weartsdk_sky-1.0.4.dist-info/METADATA
weartsdk_sky-1.0.4.dist-info/WHEEL
weartsdk_sky-1.0.4.dist-info/licenses/LICENSE.md
weartsdk_sky-1.0.4.dist-info/RECORD
