Metadata-Version: 2.3
Name: weartsdk-sky
Version: 1.0.4
Summary: WEART SDK low-level Python
Project-URL: Homepage, https://github.com/WEARTHaptics/WEART-SDK-Python
Project-URL: Issues, https://github.com/WEARTHaptics/WEART-SDK-Python/issues
Author-email: Emanuele De Santis <trunk96@gmail.com>
Maintainer: WEART
License-File: LICENSE.md
Classifier: Operating System :: Microsoft :: Windows
Classifier: Programming Language :: Python :: 3
Requires-Python: >=3.8
